{
    "95415": [
        {
            "data": {
                "parent": {
                    "parent": {
                        "parent": {
                            "index": -1,
                            "label": "snapshot"
                        },
                        "index": 2,
                        "label": "customBlock"
                    },
                    "index": 0,
                    "label": "script"
                },
                "candidate": {
                    "parent": {
                        "parent": {
                            "parent": {
                                "parent": {
                                    "parent": {
                                        "index": -1,
                                        "label": "snapshot"
                                    },
                                    "index": 2,
                                    "label": "customBlock"
                                },
                                "index": 0,
                                "label": "script"
                            },
                            "index": 3,
                            "label": "doRepeat"
                        },
                        "index": 1,
                        "label": "script"
                    },
                    "index": 2,
                    "label": "up"
                },
                "missingParent": false,
                "action": "insert",
                "index": 4,
                "from": [
                    "clear",
                    "setSize",
                    "down",
                    "doRepeat"
                ],
                "to": [
                    "clear",
                    "setSize",
                    "down",
                    "doRepeat",
                    "up"
                ],
                "type": "up"
            },
            "from": "insert: snapshot:[customBlock:[script]]: [clear, setSize, down, doRepeat] using snapshot:[customBlock:[script:[doRepeat:[script:[up]]]]]",
            "to": "insert: snapshot:[customBlock:[script]]: [clear, setSize, down, doRepeat, up] using snapshot:[customBlock:[script:[doRepeat:[script:[up]]]]]",
            "type": "highlight"
        },
        {
            "data": {
                "parent": {
                    "index": -1,
                    "label": "snapshot"
                },
                "missingParent": false,
                "action": "insert",
                "index": 3,
                "from": [
                    "stage",
                    "customBlock",
                    "customBlock"
                ],
                "to": [
                    "stage",
                    "customBlock",
                    "customBlock",
                    "var"
                ],
                "type": "var"
            },
            "from": "insert: snapshot: [stage, customBlock, customBlock]",
            "to": "insert: snapshot: [stage, customBlock, customBlock, var]",
            "type": "highlight"
        }
    ],
    "95657": [{
        "data": {
            "parent": {
                "index": -1,
                "label": "snapshot"
            },
            "missingParent": false,
            "action": "insert",
            "index": 3,
            "from": [
                "stage",
                "customBlock",
                "customBlock"
            ],
            "to": [
                "stage",
                "customBlock",
                "customBlock",
                "var"
            ],
            "type": "var"
        },
        "from": "insert: snapshot: [stage, customBlock, customBlock]",
        "to": "insert: snapshot: [stage, customBlock, customBlock, var]",
        "type": "highlight"
    }],
    "95811": [{
        "data": {
            "parent": {
                "index": -1,
                "label": "snapshot"
            },
            "missingParent": false,
            "action": "insert",
            "index": 3,
            "from": [
                "stage",
                "customBlock",
                "customBlock"
            ],
            "to": [
                "stage",
                "customBlock",
                "customBlock",
                "var"
            ],
            "type": "var"
        },
        "from": "insert: snapshot: [stage, customBlock, customBlock]",
        "to": "insert: snapshot: [stage, customBlock, customBlock, var]",
        "type": "highlight"
    }],
    "95516": [{
        "data": {
            "parent": {
                "index": -1,
                "label": "snapshot"
            },
            "missingParent": false,
            "action": "insert",
            "index": 3,
            "from": [
                "stage",
                "customBlock",
                "customBlock"
            ],
            "to": [
                "stage",
                "customBlock",
                "customBlock",
                "var"
            ],
            "type": "var"
        },
        "from": "insert: snapshot: [stage, customBlock, customBlock]",
        "to": "insert: snapshot: [stage, customBlock, customBlock, var]",
        "type": "highlight"
    }],
    "95637": [{
        "data": {
            "parent": {
                "index": -1,
                "label": "snapshot"
            },
            "missingParent": false,
            "action": "insert",
            "index": 3,
            "from": [
                "stage",
                "customBlock",
                "customBlock"
            ],
            "to": [
                "stage",
                "customBlock",
                "customBlock",
                "var"
            ],
            "type": "var"
        },
        "from": "insert: snapshot: [stage, customBlock, customBlock]",
        "to": "insert: snapshot: [stage, customBlock, customBlock, var]",
        "type": "highlight"
    }],
    "95499": [
        {
            "data": {
                "parent": {
                    "index": -1,
                    "label": "snapshot"
                },
                "missingParent": false,
                "action": "insert",
                "index": 3,
                "from": [
                    "stage",
                    "customBlock",
                    "customBlock"
                ],
                "to": [
                    "stage",
                    "customBlock",
                    "customBlock",
                    "var"
                ],
                "type": "var"
            },
            "from": "insert: snapshot: [stage, customBlock, customBlock]",
            "to": "insert: snapshot: [stage, customBlock, customBlock, var]",
            "type": "highlight"
        },
        {
            "data": {
                "parent": {
                    "parent": {
                        "parent": {
                            "index": -1,
                            "label": "snapshot"
                        },
                        "index": 2,
                        "label": "customBlock"
                    },
                    "index": 0,
                    "label": "script"
                },
                "missingParent": false,
                "action": "insert",
                "index": 4,
                "from": [
                    "clear",
                    "setSize",
                    "down",
                    "doRepeat"
                ],
                "to": [
                    "clear",
                    "setSize",
                    "down",
                    "doRepeat",
                    "up"
                ],
                "type": "up"
            },
            "from": "insert: snapshot:[customBlock:[script]]: [clear, setSize, down, doRepeat]",
            "to": "insert: snapshot:[customBlock:[script]]: [clear, setSize, down, doRepeat, up]",
            "type": "highlight"
        }
    ],
    "95653": [{
        "data": {
            "parent": {
                "index": -1,
                "label": "snapshot"
            },
            "missingParent": false,
            "action": "insert",
            "index": 3,
            "from": [
                "stage",
                "customBlock",
                "customBlock"
            ],
            "to": [
                "stage",
                "customBlock",
                "customBlock",
                "var"
            ],
            "type": "var"
        },
        "from": "insert: snapshot: [stage, customBlock, customBlock]",
        "to": "insert: snapshot: [stage, customBlock, customBlock, var]",
        "type": "highlight"
    }],
    "95797": [{
        "data": {
            "parent": {
                "index": -1,
                "label": "snapshot"
            },
            "missingParent": false,
            "action": "insert",
            "index": 3,
            "from": [
                "stage",
                "customBlock",
                "customBlock"
            ],
            "to": [
                "stage",
                "customBlock",
                "customBlock",
                "var"
            ],
            "type": "var"
        },
        "from": "insert: snapshot: [stage, customBlock, customBlock]",
        "to": "insert: snapshot: [stage, customBlock, customBlock, var]",
        "type": "highlight"
    }],
    "95633": [{
        "data": {
            "parent": {
                "index": -1,
                "label": "snapshot"
            },
            "missingParent": false,
            "action": "insert",
            "index": 3,
            "from": [
                "stage",
                "customBlock",
                "customBlock"
            ],
            "to": [
                "stage",
                "customBlock",
                "customBlock",
                "var"
            ],
            "type": "var"
        },
        "from": "insert: snapshot: [stage, customBlock, customBlock]",
        "to": "insert: snapshot: [stage, customBlock, customBlock, var]",
        "type": "highlight"
    }],
    "95831": [{
        "data": {
            "parent": {
                "index": -1,
                "label": "snapshot"
            },
            "missingParent": false,
            "action": "insert",
            "index": 3,
            "from": [
                "stage",
                "customBlock",
                "customBlock"
            ],
            "to": [
                "stage",
                "customBlock",
                "customBlock",
                "var"
            ],
            "type": "var"
        },
        "from": "insert: snapshot: [stage, customBlock, customBlock]",
        "to": "insert: snapshot: [stage, customBlock, customBlock, var]",
        "type": "highlight"
    }],
    "95513": [{
        "data": {
            "parent": {
                "index": -1,
                "label": "snapshot"
            },
            "missingParent": false,
            "action": "insert",
            "index": 3,
            "from": [
                "stage",
                "customBlock",
                "customBlock"
            ],
            "to": [
                "stage",
                "customBlock",
                "customBlock",
                "var"
            ],
            "type": "var"
        },
        "from": "insert: snapshot: [stage, customBlock, customBlock]",
        "to": "insert: snapshot: [stage, customBlock, customBlock, var]",
        "type": "highlight"
    }],
    "95451": [
        {
            "data": {
                "parent": {
                    "index": -1,
                    "label": "snapshot"
                },
                "missingParent": false,
                "action": "insert",
                "index": 3,
                "from": [
                    "stage",
                    "customBlock",
                    "customBlock"
                ],
                "to": [
                    "stage",
                    "customBlock",
                    "customBlock",
                    "var"
                ],
                "type": "var"
            },
            "from": "insert: snapshot: [stage, customBlock, customBlock]",
            "to": "insert: snapshot: [stage, customBlock, customBlock, var]",
            "type": "highlight"
        },
        {
            "data": {
                "parent": {
                    "parent": {
                        "parent": {
                            "index": -1,
                            "label": "snapshot"
                        },
                        "index": 2,
                        "label": "customBlock"
                    },
                    "index": 0,
                    "label": "script"
                },
                "missingParent": false,
                "action": "insert",
                "index": 4,
                "from": [
                    "clear",
                    "setSize",
                    "down",
                    "doRepeat"
                ],
                "to": [
                    "clear",
                    "setSize",
                    "down",
                    "doRepeat",
                    "up"
                ],
                "type": "up"
            },
            "from": "insert: snapshot:[customBlock:[script]]: [clear, setSize, down, doRepeat]",
            "to": "insert: snapshot:[customBlock:[script]]: [clear, setSize, down, doRepeat, up]",
            "type": "highlight"
        }
    ],
    "95473": [
        {
            "data": {
                "parent": {
                    "index": -1,
                    "label": "snapshot"
                },
                "missingParent": false,
                "action": "insert",
                "index": 3,
                "from": [
                    "stage",
                    "customBlock",
                    "customBlock"
                ],
                "to": [
                    "stage",
                    "customBlock",
                    "customBlock",
                    "var"
                ],
                "type": "var"
            },
            "from": "insert: snapshot: [stage, customBlock, customBlock]",
            "to": "insert: snapshot: [stage, customBlock, customBlock, var]",
            "type": "highlight"
        },
        {
            "data": {
                "parent": {
                    "parent": {
                        "parent": {
                            "index": -1,
                            "label": "snapshot"
                        },
                        "index": 2,
                        "label": "customBlock"
                    },
                    "index": 0,
                    "label": "script"
                },
                "missingParent": false,
                "action": "insert",
                "index": 4,
                "from": [
                    "clear",
                    "setSize",
                    "down",
                    "doRepeat"
                ],
                "to": [
                    "clear",
                    "setSize",
                    "down",
                    "doRepeat",
                    "up"
                ],
                "type": "up"
            },
            "from": "insert: snapshot:[customBlock:[script]]: [clear, setSize, down, doRepeat]",
            "to": "insert: snapshot:[customBlock:[script]]: [clear, setSize, down, doRepeat, up]",
            "type": "highlight"
        }
    ],
    "95497": [
        {
            "data": {
                "parent": {
                    "parent": {
                        "parent": {
                            "index": -1,
                            "label": "snapshot"
                        },
                        "index": 2,
                        "label": "customBlock"
                    },
                    "index": 0,
                    "label": "script"
                },
                "candidate": {
                    "parent": {
                        "parent": {
                            "parent": {
                                "parent": {
                                    "parent": {
                                        "index": -1,
                                        "label": "snapshot"
                                    },
                                    "index": 2,
                                    "label": "customBlock"
                                },
                                "index": 0,
                                "label": "script"
                            },
                            "index": 3,
                            "label": "doRepeat"
                        },
                        "index": 1,
                        "label": "script"
                    },
                    "index": 2,
                    "label": "up"
                },
                "missingParent": false,
                "action": "insert",
                "index": 4,
                "from": [
                    "clear",
                    "setSize",
                    "down",
                    "doRepeat"
                ],
                "to": [
                    "clear",
                    "setSize",
                    "down",
                    "doRepeat",
                    "up"
                ],
                "type": "up"
            },
            "from": "insert: snapshot:[customBlock:[script]]: [clear, setSize, down, doRepeat] using snapshot:[customBlock:[script:[doRepeat:[script:[up]]]]]",
            "to": "insert: snapshot:[customBlock:[script]]: [clear, setSize, down, doRepeat, up] using snapshot:[customBlock:[script:[doRepeat:[script:[up]]]]]",
            "type": "highlight"
        },
        {
            "data": {
                "parent": {
                    "index": -1,
                    "label": "snapshot"
                },
                "missingParent": false,
                "action": "insert",
                "index": 3,
                "from": [
                    "stage",
                    "customBlock",
                    "customBlock"
                ],
                "to": [
                    "stage",
                    "customBlock",
                    "customBlock",
                    "var"
                ],
                "type": "var"
            },
            "from": "insert: snapshot: [stage, customBlock, customBlock]",
            "to": "insert: snapshot: [stage, customBlock, customBlock, var]",
            "type": "highlight"
        }
    ],
    "95772": [{
        "data": {
            "parent": {
                "index": -1,
                "label": "snapshot"
            },
            "missingParent": false,
            "action": "insert",
            "index": 3,
            "from": [
                "stage",
                "customBlock",
                "customBlock"
            ],
            "to": [
                "stage",
                "customBlock",
                "customBlock",
                "var"
            ],
            "type": "var"
        },
        "from": "insert: snapshot: [stage, customBlock, customBlock]",
        "to": "insert: snapshot: [stage, customBlock, customBlock, var]",
        "type": "highlight"
    }],
    "95553": [{
        "data": {
            "parent": {
                "index": -1,
                "label": "snapshot"
            },
            "missingParent": false,
            "action": "insert",
            "index": 3,
            "from": [
                "stage",
                "customBlock",
                "customBlock"
            ],
            "to": [
                "stage",
                "customBlock",
                "customBlock",
                "var"
            ],
            "type": "var"
        },
        "from": "insert: snapshot: [stage, customBlock, customBlock]",
        "to": "insert: snapshot: [stage, customBlock, customBlock, var]",
        "type": "highlight"
    }],
    "95597": [{
        "data": {
            "parent": {
                "index": -1,
                "label": "snapshot"
            },
            "missingParent": false,
            "action": "insert",
            "index": 3,
            "from": [
                "stage",
                "customBlock",
                "customBlock"
            ],
            "to": [
                "stage",
                "customBlock",
                "customBlock",
                "var"
            ],
            "type": "var"
        },
        "from": "insert: snapshot: [stage, customBlock, customBlock]",
        "to": "insert: snapshot: [stage, customBlock, customBlock, var]",
        "type": "highlight"
    }],
    "95471": [
        {
            "data": {
                "parent": {
                    "index": -1,
                    "label": "snapshot"
                },
                "missingParent": false,
                "action": "insert",
                "index": 3,
                "from": [
                    "stage",
                    "customBlock",
                    "customBlock"
                ],
                "to": [
                    "stage",
                    "customBlock",
                    "customBlock",
                    "var"
                ],
                "type": "var"
            },
            "from": "insert: snapshot: [stage, customBlock, customBlock]",
            "to": "insert: snapshot: [stage, customBlock, customBlock, var]",
            "type": "highlight"
        },
        {
            "data": {
                "parent": {
                    "parent": {
                        "parent": {
                            "index": -1,
                            "label": "snapshot"
                        },
                        "index": 2,
                        "label": "customBlock"
                    },
                    "index": 0,
                    "label": "script"
                },
                "missingParent": false,
                "action": "insert",
                "index": 4,
                "from": [
                    "clear",
                    "setSize",
                    "down",
                    "doRepeat"
                ],
                "to": [
                    "clear",
                    "setSize",
                    "down",
                    "doRepeat",
                    "up"
                ],
                "type": "up"
            },
            "from": "insert: snapshot:[customBlock:[script]]: [clear, setSize, down, doRepeat]",
            "to": "insert: snapshot:[customBlock:[script]]: [clear, setSize, down, doRepeat, up]",
            "type": "highlight"
        }
    ],
    "95593": [{
        "data": {
            "parent": {
                "index": -1,
                "label": "snapshot"
            },
            "missingParent": false,
            "action": "insert",
            "index": 3,
            "from": [
                "stage",
                "customBlock",
                "customBlock"
            ],
            "to": [
                "stage",
                "customBlock",
                "customBlock",
                "var"
            ],
            "type": "var"
        },
        "from": "insert: snapshot: [stage, customBlock, customBlock]",
        "to": "insert: snapshot: [stage, customBlock, customBlock, var]",
        "type": "highlight"
    }],
    "95629": [{
        "data": {
            "parent": {
                "index": -1,
                "label": "snapshot"
            },
            "missingParent": false,
            "action": "insert",
            "index": 3,
            "from": [
                "stage",
                "customBlock",
                "customBlock"
            ],
            "to": [
                "stage",
                "customBlock",
                "customBlock",
                "var"
            ],
            "type": "var"
        },
        "from": "insert: snapshot: [stage, customBlock, customBlock]",
        "to": "insert: snapshot: [stage, customBlock, customBlock, var]",
        "type": "highlight"
    }],
    "95906": [
        {
            "data": {
                "parent": {
                    "index": -1,
                    "label": "snapshot"
                },
                "missingParent": false,
                "action": "insert",
                "index": 3,
                "from": [
                    "stage",
                    "customBlock",
                    "customBlock"
                ],
                "to": [
                    "stage",
                    "customBlock",
                    "customBlock",
                    "var"
                ],
                "type": "var"
            },
            "from": "insert: snapshot: [stage, customBlock, customBlock]",
            "to": "insert: snapshot: [stage, customBlock, customBlock, var]",
            "type": "highlight"
        },
        {
            "data": {
                "parent": {
                    "parent": {
                        "parent": {
                            "index": -1,
                            "label": "snapshot"
                        },
                        "index": 2,
                        "label": "customBlock"
                    },
                    "index": 0,
                    "label": "script"
                },
                "node": {
                    "parent": {
                        "parent": {
                            "parent": {
                                "index": -1,
                                "label": "snapshot"
                            },
                            "index": 2,
                            "label": "customBlock"
                        },
                        "index": 0,
                        "label": "script"
                    },
                    "index": 1,
                    "label": "gotoXY"
                },
                "action": "delete"
            },
            "from": "delete: snapshot:[customBlock:[script]]: [clear, gotoXY, setSize, down, doRepeat, up]",
            "to": "delete: snapshot:[customBlock:[script]]: [clear, setSize, down, doRepeat, up]",
            "type": "highlight"
        }
    ],
    "95503": [
        {
            "data": {
                "parent": {
                    "index": -1,
                    "label": "snapshot"
                },
                "missingParent": false,
                "action": "insert",
                "index": 3,
                "from": [
                    "stage",
                    "customBlock",
                    "customBlock"
                ],
                "to": [
                    "stage",
                    "customBlock",
                    "customBlock",
                    "var"
                ],
                "type": "var"
            },
            "from": "insert: snapshot: [stage, customBlock, customBlock]",
            "to": "insert: snapshot: [stage, customBlock, customBlock, var]",
            "type": "highlight"
        },
        {
            "data": {
                "parent": {
                    "parent": {
                        "parent": {
                            "index": -1,
                            "label": "snapshot"
                        },
                        "index": 2,
                        "label": "customBlock"
                    },
                    "index": 0,
                    "label": "script"
                },
                "missingParent": false,
                "action": "insert",
                "index": 4,
                "from": [
                    "clear",
                    "setSize",
                    "down",
                    "doRepeat"
                ],
                "to": [
                    "clear",
                    "setSize",
                    "down",
                    "doRepeat",
                    "up"
                ],
                "type": "up"
            },
            "from": "insert: snapshot:[customBlock:[script]]: [clear, setSize, down, doRepeat]",
            "to": "insert: snapshot:[customBlock:[script]]: [clear, setSize, down, doRepeat, up]",
            "type": "highlight"
        }
    ],
    "95625": [{
        "data": {
            "parent": {
                "index": -1,
                "label": "snapshot"
            },
            "missingParent": false,
            "action": "insert",
            "index": 3,
            "from": [
                "stage",
                "customBlock",
                "customBlock"
            ],
            "to": [
                "stage",
                "customBlock",
                "customBlock",
                "var"
            ],
            "type": "var"
        },
        "from": "insert: snapshot: [stage, customBlock, customBlock]",
        "to": "insert: snapshot: [stage, customBlock, customBlock, var]",
        "type": "highlight"
    }],
    "95549": [{
        "data": {
            "parent": {
                "index": -1,
                "label": "snapshot"
            },
            "missingParent": false,
            "action": "insert",
            "index": 3,
            "from": [
                "stage",
                "customBlock",
                "customBlock"
            ],
            "to": [
                "stage",
                "customBlock",
                "customBlock",
                "var"
            ],
            "type": "var"
        },
        "from": "insert: snapshot: [stage, customBlock, customBlock]",
        "to": "insert: snapshot: [stage, customBlock, customBlock, var]",
        "type": "highlight"
    }],
    "95649": [{
        "data": {
            "parent": {
                "index": -1,
                "label": "snapshot"
            },
            "missingParent": false,
            "action": "insert",
            "index": 3,
            "from": [
                "stage",
                "customBlock",
                "customBlock"
            ],
            "to": [
                "stage",
                "customBlock",
                "customBlock",
                "var"
            ],
            "type": "var"
        },
        "from": "insert: snapshot: [stage, customBlock, customBlock]",
        "to": "insert: snapshot: [stage, customBlock, customBlock, var]",
        "type": "highlight"
    }],
    "95423": [
        {
            "data": {
                "parent": {
                    "parent": {
                        "parent": {
                            "index": -1,
                            "label": "snapshot"
                        },
                        "index": 2,
                        "label": "customBlock"
                    },
                    "index": 0,
                    "label": "script"
                },
                "candidate": {
                    "parent": {
                        "parent": {
                            "parent": {
                                "parent": {
                                    "parent": {
                                        "index": -1,
                                        "label": "snapshot"
                                    },
                                    "index": 2,
                                    "label": "customBlock"
                                },
                                "index": 0,
                                "label": "script"
                            },
                            "index": 3,
                            "label": "doRepeat"
                        },
                        "index": 1,
                        "label": "script"
                    },
                    "index": 2,
                    "label": "up"
                },
                "missingParent": false,
                "action": "insert",
                "index": 4,
                "from": [
                    "clear",
                    "setSize",
                    "down",
                    "doRepeat"
                ],
                "to": [
                    "clear",
                    "setSize",
                    "down",
                    "doRepeat",
                    "up"
                ],
                "type": "up"
            },
            "from": "insert: snapshot:[customBlock:[script]]: [clear, setSize, down, doRepeat] using snapshot:[customBlock:[script:[doRepeat:[script:[up]]]]]",
            "to": "insert: snapshot:[customBlock:[script]]: [clear, setSize, down, doRepeat, up] using snapshot:[customBlock:[script:[doRepeat:[script:[up]]]]]",
            "type": "highlight"
        },
        {
            "data": {
                "parent": {
                    "index": -1,
                    "label": "snapshot"
                },
                "missingParent": false,
                "action": "insert",
                "index": 3,
                "from": [
                    "stage",
                    "customBlock",
                    "customBlock"
                ],
                "to": [
                    "stage",
                    "customBlock",
                    "customBlock",
                    "var"
                ],
                "type": "var"
            },
            "from": "insert: snapshot: [stage, customBlock, customBlock]",
            "to": "insert: snapshot: [stage, customBlock, customBlock, var]",
            "type": "highlight"
        }
    ],
    "95621": [{
        "data": {
            "parent": {
                "index": -1,
                "label": "snapshot"
            },
            "missingParent": false,
            "action": "insert",
            "index": 3,
            "from": [
                "stage",
                "customBlock",
                "customBlock"
            ],
            "to": [
                "stage",
                "customBlock",
                "customBlock",
                "var"
            ],
            "type": "var"
        },
        "from": "insert: snapshot: [stage, customBlock, customBlock]",
        "to": "insert: snapshot: [stage, customBlock, customBlock, var]",
        "type": "highlight"
    }],
    "95501": [
        {
            "data": {
                "parent": {
                    "index": -1,
                    "label": "snapshot"
                },
                "missingParent": false,
                "action": "insert",
                "index": 3,
                "from": [
                    "stage",
                    "customBlock",
                    "customBlock"
                ],
                "to": [
                    "stage",
                    "customBlock",
                    "customBlock",
                    "var"
                ],
                "type": "var"
            },
            "from": "insert: snapshot: [stage, customBlock, customBlock]",
            "to": "insert: snapshot: [stage, customBlock, customBlock, var]",
            "type": "highlight"
        },
        {
            "data": {
                "parent": {
                    "parent": {
                        "parent": {
                            "index": -1,
                            "label": "snapshot"
                        },
                        "index": 2,
                        "label": "customBlock"
                    },
                    "index": 0,
                    "label": "script"
                },
                "missingParent": false,
                "action": "insert",
                "index": 4,
                "from": [
                    "clear",
                    "setSize",
                    "down",
                    "doRepeat"
                ],
                "to": [
                    "clear",
                    "setSize",
                    "down",
                    "doRepeat",
                    "up"
                ],
                "type": "up"
            },
            "from": "insert: snapshot:[customBlock:[script]]: [clear, setSize, down, doRepeat]",
            "to": "insert: snapshot:[customBlock:[script]]: [clear, setSize, down, doRepeat, up]",
            "type": "highlight"
        }
    ],
    "95589": [{
        "data": {
            "parent": {
                "index": -1,
                "label": "snapshot"
            },
            "missingParent": false,
            "action": "insert",
            "index": 3,
            "from": [
                "stage",
                "customBlock",
                "customBlock"
            ],
            "to": [
                "stage",
                "customBlock",
                "customBlock",
                "var"
            ],
            "type": "var"
        },
        "from": "insert: snapshot: [stage, customBlock, customBlock]",
        "to": "insert: snapshot: [stage, customBlock, customBlock, var]",
        "type": "highlight"
    }],
    "95469": [
        {
            "data": {
                "parent": {
                    "index": -1,
                    "label": "snapshot"
                },
                "missingParent": false,
                "action": "insert",
                "index": 3,
                "from": [
                    "stage",
                    "customBlock",
                    "customBlock"
                ],
                "to": [
                    "stage",
                    "customBlock",
                    "customBlock",
                    "var"
                ],
                "type": "var"
            },
            "from": "insert: snapshot: [stage, customBlock, customBlock]",
            "to": "insert: snapshot: [stage, customBlock, customBlock, var]",
            "type": "highlight"
        },
        {
            "data": {
                "parent": {
                    "parent": {
                        "parent": {
                            "index": -1,
                            "label": "snapshot"
                        },
                        "index": 2,
                        "label": "customBlock"
                    },
                    "index": 0,
                    "label": "script"
                },
                "missingParent": false,
                "action": "insert",
                "index": 4,
                "from": [
                    "clear",
                    "setSize",
                    "down",
                    "doRepeat"
                ],
                "to": [
                    "clear",
                    "setSize",
                    "down",
                    "doRepeat",
                    "up"
                ],
                "type": "up"
            },
            "from": "insert: snapshot:[customBlock:[script]]: [clear, setSize, down, doRepeat]",
            "to": "insert: snapshot:[customBlock:[script]]: [clear, setSize, down, doRepeat, up]",
            "type": "highlight"
        }
    ],
    "95645": [{
        "data": {
            "parent": {
                "index": -1,
                "label": "snapshot"
            },
            "missingParent": false,
            "action": "insert",
            "index": 3,
            "from": [
                "stage",
                "customBlock",
                "customBlock"
            ],
            "to": [
                "stage",
                "customBlock",
                "customBlock",
                "var"
            ],
            "type": "var"
        },
        "from": "insert: snapshot: [stage, customBlock, customBlock]",
        "to": "insert: snapshot: [stage, customBlock, customBlock, var]",
        "type": "highlight"
    }],
    "95821": [{
        "data": {
            "parent": {
                "index": -1,
                "label": "snapshot"
            },
            "missingParent": false,
            "action": "insert",
            "index": 3,
            "from": [
                "stage",
                "customBlock",
                "customBlock"
            ],
            "to": [
                "stage",
                "customBlock",
                "customBlock",
                "var"
            ],
            "type": "var"
        },
        "from": "insert: snapshot: [stage, customBlock, customBlock]",
        "to": "insert: snapshot: [stage, customBlock, customBlock, var]",
        "type": "highlight"
    }],
    "95865": [{
        "data": {
            "parent": {
                "index": -1,
                "label": "snapshot"
            },
            "missingParent": false,
            "action": "insert",
            "index": 3,
            "from": [
                "stage",
                "customBlock",
                "customBlock"
            ],
            "to": [
                "stage",
                "customBlock",
                "customBlock",
                "var"
            ],
            "type": "var"
        },
        "from": "insert: snapshot: [stage, customBlock, customBlock]",
        "to": "insert: snapshot: [stage, customBlock, customBlock, var]",
        "type": "highlight"
    }],
    "95661": [{
        "data": {
            "parent": {
                "index": -1,
                "label": "snapshot"
            },
            "missingParent": false,
            "action": "insert",
            "index": 3,
            "from": [
                "stage",
                "customBlock",
                "customBlock"
            ],
            "to": [
                "stage",
                "customBlock",
                "customBlock",
                "var"
            ],
            "type": "var"
        },
        "from": "insert: snapshot: [stage, customBlock, customBlock]",
        "to": "insert: snapshot: [stage, customBlock, customBlock, var]",
        "type": "highlight"
    }],
    "96156": [
        {
            "data": {
                "parent": {
                    "index": -1,
                    "label": "snapshot"
                },
                "missingParent": false,
                "action": "insert",
                "index": 3,
                "from": [
                    "stage",
                    "customBlock",
                    "customBlock"
                ],
                "to": [
                    "stage",
                    "customBlock",
                    "customBlock",
                    "var"
                ],
                "type": "var"
            },
            "from": "insert: snapshot: [stage, customBlock, customBlock]",
            "to": "insert: snapshot: [stage, customBlock, customBlock, var]",
            "type": "highlight"
        },
        {
            "data": {
                "parent": {
                    "parent": {
                        "parent": {
                            "index": -1,
                            "label": "snapshot"
                        },
                        "index": 2,
                        "label": "customBlock"
                    },
                    "index": 0,
                    "label": "script"
                },
                "node": {
                    "parent": {
                        "parent": {
                            "parent": {
                                "index": -1,
                                "label": "snapshot"
                            },
                            "index": 2,
                            "label": "customBlock"
                        },
                        "index": 0,
                        "label": "script"
                    },
                    "index": 1,
                    "label": "gotoXY"
                },
                "action": "delete"
            },
            "from": "delete: snapshot:[customBlock:[script]]: [clear, gotoXY, setSize, down, doRepeat, up]",
            "to": "delete: snapshot:[customBlock:[script]]: [clear, setSize, down, doRepeat, up]",
            "type": "highlight"
        }
    ],
    "95585": [{
        "data": {
            "parent": {
                "index": -1,
                "label": "snapshot"
            },
            "missingParent": false,
            "action": "insert",
            "index": 3,
            "from": [
                "stage",
                "customBlock",
                "customBlock"
            ],
            "to": [
                "stage",
                "customBlock",
                "customBlock",
                "var"
            ],
            "type": "var"
        },
        "from": "insert: snapshot: [stage, customBlock, customBlock]",
        "to": "insert: snapshot: [stage, customBlock, customBlock, var]",
        "type": "highlight"
    }],
    "95542": [{
        "data": {
            "parent": {
                "index": -1,
                "label": "snapshot"
            },
            "missingParent": false,
            "action": "insert",
            "index": 3,
            "from": [
                "stage",
                "customBlock",
                "customBlock"
            ],
            "to": [
                "stage",
                "customBlock",
                "customBlock",
                "var"
            ],
            "type": "var"
        },
        "from": "insert: snapshot: [stage, customBlock, customBlock]",
        "to": "insert: snapshot: [stage, customBlock, customBlock, var]",
        "type": "highlight"
    }],
    "95641": [{
        "data": {
            "parent": {
                "index": -1,
                "label": "snapshot"
            },
            "missingParent": false,
            "action": "insert",
            "index": 3,
            "from": [
                "stage",
                "customBlock",
                "customBlock"
            ],
            "to": [
                "stage",
                "customBlock",
                "customBlock",
                "var"
            ],
            "type": "var"
        },
        "from": "insert: snapshot: [stage, customBlock, customBlock]",
        "to": "insert: snapshot: [stage, customBlock, customBlock, var]",
        "type": "highlight"
    }],
    "95861": [{
        "data": {
            "parent": {
                "index": -1,
                "label": "snapshot"
            },
            "missingParent": false,
            "action": "insert",
            "index": 3,
            "from": [
                "stage",
                "customBlock",
                "customBlock"
            ],
            "to": [
                "stage",
                "customBlock",
                "customBlock",
                "var"
            ],
            "type": "var"
        },
        "from": "insert: snapshot: [stage, customBlock, customBlock]",
        "to": "insert: snapshot: [stage, customBlock, customBlock, var]",
        "type": "highlight"
    }],
    "96151": [
        {
            "data": {
                "parent": {
                    "index": -1,
                    "label": "snapshot"
                },
                "missingParent": false,
                "action": "insert",
                "index": 3,
                "from": [
                    "stage",
                    "customBlock",
                    "customBlock"
                ],
                "to": [
                    "stage",
                    "customBlock",
                    "customBlock",
                    "var"
                ],
                "type": "var"
            },
            "from": "insert: snapshot: [stage, customBlock, customBlock]",
            "to": "insert: snapshot: [stage, customBlock, customBlock, var]",
            "type": "highlight"
        },
        {
            "data": {
                "parent": {
                    "parent": {
                        "parent": {
                            "index": -1,
                            "label": "snapshot"
                        },
                        "index": 2,
                        "label": "customBlock"
                    },
                    "index": 0,
                    "label": "script"
                },
                "node": {
                    "parent": {
                        "parent": {
                            "parent": {
                                "index": -1,
                                "label": "snapshot"
                            },
                            "index": 2,
                            "label": "customBlock"
                        },
                        "index": 0,
                        "label": "script"
                    },
                    "index": 1,
                    "label": "gotoXY"
                },
                "action": "delete"
            },
            "from": "delete: snapshot:[customBlock:[script]]: [clear, gotoXY, setSize, down, doRepeat, up]",
            "to": "delete: snapshot:[customBlock:[script]]: [clear, setSize, down, doRepeat, up]",
            "type": "highlight"
        }
    ],
    "95482": [
        {
            "data": {
                "parent": {
                    "index": -1,
                    "label": "snapshot"
                },
                "missingParent": false,
                "action": "insert",
                "index": 3,
                "from": [
                    "stage",
                    "customBlock",
                    "customBlock"
                ],
                "to": [
                    "stage",
                    "customBlock",
                    "customBlock",
                    "var"
                ],
                "type": "var"
            },
            "from": "insert: snapshot: [stage, customBlock, customBlock]",
            "to": "insert: snapshot: [stage, customBlock, customBlock, var]",
            "type": "highlight"
        },
        {
            "data": {
                "parent": {
                    "parent": {
                        "parent": {
                            "index": -1,
                            "label": "snapshot"
                        },
                        "index": 2,
                        "label": "customBlock"
                    },
                    "index": 0,
                    "label": "script"
                },
                "missingParent": false,
                "action": "insert",
                "index": 4,
                "from": [
                    "clear",
                    "setSize",
                    "down",
                    "doRepeat"
                ],
                "to": [
                    "clear",
                    "setSize",
                    "down",
                    "doRepeat",
                    "up"
                ],
                "type": "up"
            },
            "from": "insert: snapshot:[customBlock:[script]]: [clear, setSize, down, doRepeat]",
            "to": "insert: snapshot:[customBlock:[script]]: [clear, setSize, down, doRepeat, up]",
            "type": "highlight"
        }
    ],
    "96171": [
        {
            "data": {
                "parent": {
                    "index": -1,
                    "label": "snapshot"
                },
                "missingParent": false,
                "action": "insert",
                "index": 3,
                "from": [
                    "stage",
                    "customBlock",
                    "customBlock"
                ],
                "to": [
                    "stage",
                    "customBlock",
                    "customBlock",
                    "var"
                ],
                "type": "var"
            },
            "from": "insert: snapshot: [stage, customBlock, customBlock]",
            "to": "insert: snapshot: [stage, customBlock, customBlock, var]",
            "type": "highlight"
        },
        {
            "data": {
                "parent": {
                    "parent": {
                        "parent": {
                            "index": -1,
                            "label": "snapshot"
                        },
                        "index": 2,
                        "label": "customBlock"
                    },
                    "index": 0,
                    "label": "script"
                },
                "node": {
                    "parent": {
                        "parent": {
                            "parent": {
                                "index": -1,
                                "label": "snapshot"
                            },
                            "index": 2,
                            "label": "customBlock"
                        },
                        "index": 0,
                        "label": "script"
                    },
                    "index": 1,
                    "label": "gotoXY"
                },
                "action": "delete"
            },
            "from": "delete: snapshot:[customBlock:[script]]: [clear, gotoXY, setSize, down, doRepeat, up]",
            "to": "delete: snapshot:[customBlock:[script]]: [clear, setSize, down, doRepeat, up]",
            "type": "highlight"
        }
    ]
}